aiogram_smart_messages/builder.py
aiogram_smart_messages/decorators.py
aiogram_smart_messages/loader.py
aiogram_smart_messages/logger.py
aiogram_smart_messages/message_engine.py
aiogram_smart_messages/middlewares/__init__.py
aiogram_smart_messages/middlewares/message_engine_middleware.py
aiogram_smart_messages/renderer/__init__.py
aiogram_smart_messages/renderer/bot_messages.py
aiogram_smart_messages-0.2.0.dist-info/licenses/LICENSE
aiogram_smart_messages-0.2.0.dist-info/METADATA
aiogram_smart_messages-0.2.0.dist-info/WHEEL
aiogram_smart_messages-0.2.0.dist-info/top_level.txt
aiogram_smart_messages-0.2.0.dist-info/RECORD
