Metadata-Version: 2.4
Name: aiogram-smart-messages
Version: 0.2.0
Summary: Smart message renderer for Aiogram with keyboard builder and JSON loader
Author-email: Kriva <your.email@example.com>
License: MIT
Requires-Python: >=3.11
License-File: LICENSE
Requires-Dist: aiogram>=3.0
Dynamic: license-file
